<?xml version="1.0" encoding="UTF-8"?>
<objects serializationModel="Studio.02.01.00">
	<object class="AudioFile" id="{2005376b-3ca7-4e10-a6c1-b255e2651f7f}">
		<property name="assetPath">
			<value>SFX/Atmos/Walla/148092-CrisisCrowd-ConcrnSlghtPn.wav</value>
		</property>
		<property name="frequencyInKHz">
			<value>44.0999985</value>
		</property>
		<property name="channelCount">
			<value>2</value>
		</property>
		<property name="length">
			<value>31.207619047619048</value>
		</property>
		<relationship name="masterAssetFolder">
			<destination>{6cefe92b-0ba8-439b-80cc-815142e84d0c}</destination>
		</relationship>
	</object>
</objects>
